djangotenberg/__init__.py
djangotenberg/apps.py
djangotenberg/client.py
djangotenberg/conf.py
djangotenberg/exceptions.py
djangotenberg/retry.py
djangotenberg/serializers.py
djangotenberg/urls.py
djangotenberg/properties/__init__.py
djangotenberg/properties/builder.py
djangotenberg/properties/properties.py
djangotenberg/properties/validate.py
djangotenberg/views/__init__.py
djangotenberg/views/base.py
djangotenberg/views/pdf.py
djangotenberg-0.2.0.dist-info/licenses/LICENSE
djangotenberg-0.2.0.dist-info/METADATA
djangotenberg-0.2.0.dist-info/WHEEL
djangotenberg-0.2.0.dist-info/top_level.txt
djangotenberg-0.2.0.dist-info/RECORD
