Metadata-Version: 2.4
Name: djangotenberg
Version: 0.2.0
Summary: Django Gotenberg
Author-email: Nutchapon Metmaolee <nutchapon.met1002@gmail.com>
License: MIT
Classifier: Framework :: Django
Classifier: Framework :: Django :: 4.2
Classifier: Programming Language :: Python :: 3
Classifier: License :: OSI Approved :: MIT License
Requires-Python: >=3.9
License-File: LICENSE
Requires-Dist: Django>=4.2
Requires-Dist: djangorestframework>=3.16
Requires-Dist: requests>=2.32
Dynamic: license-file
